django_easy_pjax-1.3.0.dist-info/DESCRIPTION.rst
django_easy_pjax-1.3.0.dist-info/LICENSE.txt
django_easy_pjax-1.3.0.dist-info/METADATA
django_easy_pjax-1.3.0.dist-info/RECORD
django_easy_pjax-1.3.0.dist-info/WHEEL
django_easy_pjax-1.3.0.dist-info/metadata.json
django_easy_pjax-1.3.0.dist-info/top_level.txt
easy_pjax/__init__.py
easy_pjax/apps.py
easy_pjax/middleware.py
easy_pjax/models.py
easy_pjax/templates/pjax_base.html
easy_pjax/templatetags/__init__.py
easy_pjax/templatetags/pjax_tags.py
